tree_distance.cpython-37m-x86_64-linux-gnu.so
tree_distance-1.0.12.dist-info/RECORD
tree_distance-1.0.12.dist-info/WHEEL
tree_distance-1.0.12.dist-info/top_level.txt
tree_distance-1.0.12.dist-info/LICENSE.txt
tree_distance-1.0.12.dist-info/METADATA
