Metadata-Version: 2.1
Name: tree-distance
Version: 1.0.12
Summary: Wrapper for GTP tree distances in c++
Home-page: https://github.com/kgori/tree_distance.git
Author: Kevin Gori
Author-email: kgori@ebi.ac.uk
License-File: LICENSE.txt
Requires-Dist: cython
